jutge/__init__.py
jutge/tokenizer.py
jutge/utils.py
jutge-2.1.dist-info/LICENSE.txt
jutge-2.1.dist-info/METADATA
jutge-2.1.dist-info/WHEEL
jutge-2.1.dist-info/top_level.txt
jutge-2.1.dist-info/RECORD
