Metadata-Version: 2.1
Name: jutge
Version: 2.1
Summary: Simple functions to read input from Python
Home-page: https://github.com/jutge-org/jutge-python
Author: Jordi Petit et al
Author-email: jpetit@cs.upc.edu
License: Apache
Download-URL: https://github.com/jutge-org/jutge-python/tarball/2.1
Keywords: jutge,jutge.org,education,input
Platform: UNKNOWN
Classifier: Development Status :: 5 - Production/Stable
Classifier: Environment :: Console
Classifier: Intended Audience :: Education
Classifier: License :: OSI Approved :: Apache Software License
Classifier: Operating System :: OS Independent
Classifier: Programming Language :: Python
Classifier: Programming Language :: Python :: 2
Classifier: Programming Language :: Python :: 2.7
Classifier: Programming Language :: Python :: 3
Classifier: Programming Language :: Python :: 3.4
Classifier: Programming Language :: Python :: 3.5
Classifier: Programming Language :: Python :: 3.7
Classifier: Topic :: Education
Requires-Dist: future (>=0.17)
Requires-Dist: enum34
